jps_test_artifact_python_utils/__init__.py
jps_test_artifact_python_utils/create_md5_manifest.py
jps_test_artifact_python_utils/setup_functional_test.py
jps_test_artifact_python_utils/verify_md5_manifest.py
jps_test_artifact_python_utils-0.1.3.dist-info/licenses/LICENSE
jps_test_artifact_python_utils-0.1.3.dist-info/METADATA
jps_test_artifact_python_utils-0.1.3.dist-info/WHEEL
jps_test_artifact_python_utils-0.1.3.dist-info/entry_points.txt
jps_test_artifact_python_utils-0.1.3.dist-info/top_level.txt
jps_test_artifact_python_utils-0.1.3.dist-info/RECORD
