Metadata-Version: 2.4
Name: jps-test-artifact-python-utils
Version: 0.1.3
Summary: Utilities for creating, verifying, and managing test artifact directories and manifests.
Author-email: Jaideep Sundaram <jai.python3@gmail.com>
Maintainer-email: Jaideep Sundaram <jai.python3@gmail.com>
License-Expression: MIT
Project-URL: Homepage, https://github.com/jai-python3/jps-test-artifact-python-utils
Project-URL: Repository, https://github.com/jai-python3/jps-test-artifact-python-utils
Project-URL: Issues, https://github.com/jai-python3/jps-test-artifact-python-utils/issues
Keywords: test,artifacts,md5,manifest,automation,verification
Requires-Python: >=3.9
License-File: LICENSE
Requires-Dist: typer>=0.12.5
Provides-Extra: test
Requires-Dist: pytest>=8.0.0; extra == "test"
Provides-Extra: dev
Requires-Dist: flake8>=7.0.0; extra == "dev"
Requires-Dist: black>=24.0.0; extra == "dev"
Requires-Dist: build>=1.2.1; extra == "dev"
Requires-Dist: twine>=5.0.0; extra == "dev"
Requires-Dist: pre-commit>=3.7.0; extra == "dev"
Requires-Dist: pytest>=8.0.0; extra == "dev"
Requires-Dist: pytest-cov>=4.1.0; extra == "dev"
Requires-Dist: typer>=0.12.5; extra == "dev"
Requires-Dist: isort>=5.13.0; extra == "dev"
Requires-Dist: codecov>=2.1.13; extra == "dev"
Requires-Dist: autoflake>=2.3.1; extra == "dev"
Requires-Dist: bandit>=1.7.9; extra == "dev"
Requires-Dist: vulture>=2.11; extra == "dev"
Requires-Dist: flynt>=1.0.1; extra == "dev"
Requires-Dist: pydocstyle>=6.3.0; extra == "dev"
Requires-Dist: darglint>=1.8.1; extra == "dev"
Requires-Dist: mypy>=1.12.1; extra == "dev"
Dynamic: license-file
